airtrik/__init__.py
airtrik/iot.py
airtrik-0.1.6.dist-info/LICENSE
airtrik-0.1.6.dist-info/METADATA
airtrik-0.1.6.dist-info/WHEEL
airtrik-0.1.6.dist-info/top_level.txt
airtrik-0.1.6.dist-info/RECORD
