Metadata-Version: 2.1
Name: airtrik
Version: 0.1.6
Summary: Connect IoT Devices to cloud and manage from anywhere.
Home-page: https://github.com/airtrik/python
Author: Vishal Pandey
Author-email: hello@airtrik.com
License: UNKNOWN
Platform: UNKNOWN
Classifier: Programming Language :: Python :: 3
Classifier: License :: OSI Approved :: MIT License
Classifier: Operating System :: OS Independent
Requires-Python: >=3.5
Requires-Dist: paho-mqtt
Requires-Dist: requests
